LICENSE
MANIFEST.in
README.md
setup.py
bin/lenscap
lenscap/__init__.py
lenscap/core.py
lenscap.egg-info/PKG-INFO
lenscap.egg-info/SOURCES.txt
lenscap.egg-info/dependency_links.txt
lenscap.egg-info/requires.txt
lenscap.egg-info/top_level.txt
lenscap/templates/skeleton.css
lenscap/templates/style.css
lenscap/templates/default/base.html
lenscap/templates/default/rows.html
lenscap/templates/narrow/base.html
lenscap/templates/narrow/rows.html