Metadata-Version: 2.1
Name: lenscap
Version: 0.3.0
Summary: static photo story generator
Home-page: UNKNOWN
Author: Honza Pokorny
Author-email: me@honza.ca
Maintainer: Honza Pokorny
Maintainer-email: me@honza.ca
License: UNKNOWN
Platform: UNKNOWN
